mo_installer/__init__.py
mo_installer/builder.py
mo_installer/version.py
mo_installer/vendor/__init__.py
mo_installer/vendor/msgfmt.py
mo_installer-0.3.0.dist-info/LICENSE
mo_installer-0.3.0.dist-info/METADATA
mo_installer-0.3.0.dist-info/WHEEL
mo_installer-0.3.0.dist-info/entry_points.txt
mo_installer-0.3.0.dist-info/top_level.txt
mo_installer-0.3.0.dist-info/RECORD
