Metadata-Version: 2.1
Name: mo-installer
Version: 0.3.0
Summary: Smoothly integrates mo files in setuptools packaging
Home-page: https://github.com/s-ball/mo_installer
Author: s-ball
Author-email: s-ball@laposte.net
License: MIT License
Project-URL: Changelog, https://github.com/s-ball/mo_installer/blob/master/CHANGES.txt
Platform: UNKNOWN
Classifier: Development Status :: 4 - Beta
Classifier: Programming Language :: Python :: 3
Classifier: Programming Language :: Python :: 3.3
Classifier: Programming Language :: Python :: 3.4
Classifier: Programming Language :: Python :: 3.5
Classifier: Programming Language :: Python :: 3.6
Classifier: Programming Language :: Python :: 3.7
Classifier: Environment :: Console
Classifier: Intended Audience :: Developers
Classifier: License :: OSI Approved :: MIT License
Classifier: Operating System :: OS Independent
Classifier: Topic :: Software Development :: Internationalization
Requires-Python: >=3
